LICENSE.md
MANIFEST.in
README.md
example.py
setup.cfg
setup.py
bin/__init__.py
bin/chirp-audio-read
bin/chirp-audio-write
bin/chirp-receive
bin/chirp-send
chirpsdk/__init__.py
chirpsdk/_chirpsdk.c
chirpsdk/audio.py
chirpsdk/chirpsdk.py
chirpsdk/exceptions.py
chirpsdk/network.py
chirpsdk.egg-info/PKG-INFO
chirpsdk.egg-info/SOURCES.txt
chirpsdk.egg-info/dependency_links.txt
chirpsdk.egg-info/requires.txt
chirpsdk.egg-info/top_level.txt
chirpsdk/include/chirp_sdk_events.h
chirpsdk/libraries/darwin/libchirp-sdk-shared.dylib
chirpsdk/libraries/linux/libchirp-sdk-shared.so
chirpsdk/libraries/rpi6/libchirp-sdk-shared.so
chirpsdk/libraries/rpi7/libchirp-sdk-shared.so
chirpsdk/libraries/win32/libchirp-sdk-shared.dll
chirpsdk/libraries/win64/libchirp-sdk-shared.dll
tests/__init__.py
tests/test_chirpsdk.py